cwltool/__init__.py
cwltool/__main__.py
cwltool/_version.py
cwltool/argparser.py
cwltool/builder.py
cwltool/checker.py
cwltool/command_line_tool.py
cwltool/context.py
cwltool/cuda.py
cwltool/cwlrdf.py
cwltool/cwlviewer.py
cwltool/docker.py
cwltool/docker_id.py
cwltool/env_to_stdout.py
cwltool/errors.py
cwltool/executors.py
cwltool/extensions-v1.1.yml
cwltool/extensions-v1.2.yml
cwltool/extensions-v1.3.yml
cwltool/extensions.yml
cwltool/factory.py
cwltool/flatten.py
cwltool/hello.simg
cwltool/job.py
cwltool/load_tool.py
cwltool/loghandler.py
cwltool/main.py
cwltool/mpi.py
cwltool/mutation.py
cwltool/pack.py
cwltool/pathmapper.py
cwltool/process.py
cwltool/procgenerator.py
cwltool/py.typed
cwltool/resolver.py
cwltool/run_job.py
cwltool/secrets.py
cwltool/singularity.py
cwltool/singularity_utils.py
cwltool/software_requirements.py
cwltool/stdfsaccess.py
cwltool/subgraph.py
cwltool/task_queue.py
cwltool/udocker.py
cwltool/update.py
cwltool/utils.py
cwltool/validate_js.py
cwltool/workflow.py
cwltool/workflow_job.py
cwltool/cwlprov/__init__.py
cwltool/cwlprov/provenance_constants.py
cwltool/cwlprov/provenance_profile.py
cwltool/cwlprov/ro.py
cwltool/cwlprov/writablebagfile.py
cwltool/jshint/jshint.js
cwltool/jshint/jshint_wrapper.js
cwltool/rdfqueries/get_inner_edges.sparql
cwltool/rdfqueries/get_input_edges.sparql
cwltool/rdfqueries/get_output_edges.sparql
cwltool/rdfqueries/get_root.sparql
cwltool/schemas/CITATION
cwltool/schemas/CODE_OF_CONDUCT.md
cwltool/schemas/LICENSE.txt
cwltool/schemas/README.md
cwltool/schemas/v1.0/CommandLineTool-standalone.yml
cwltool/schemas/v1.0/CommandLineTool.yml
cwltool/schemas/v1.0/CommonWorkflowLanguage.yml
cwltool/schemas/v1.0/Process.yml
cwltool/schemas/v1.0/README.md
cwltool/schemas/v1.0/UserGuide.yml
cwltool/schemas/v1.0/Workflow.yml
cwltool/schemas/v1.0/concepts.md
cwltool/schemas/v1.0/conformance_test_v1.0.yaml
cwltool/schemas/v1.0/contrib.md
cwltool/schemas/v1.0/intro.md
cwltool/schemas/v1.0/invocation.md
cwltool-3.1.20260108082145.dist-info/licenses/LICENSE.txt
cwltool-3.1.20260108082145.dist-info/METADATA
cwltool-3.1.20260108082145.dist-info/WHEEL
cwltool-3.1.20260108082145.dist-info/entry_points.txt
cwltool-3.1.20260108082145.dist-info/top_level.txt
cwltool-3.1.20260108082145.dist-info/zip-safe
cwltool-3.1.20260108082145.dist-info/RECORD
