Metadata-Version: 2.4
Name: cwltool
Version: 3.1.20260108082145
Summary: Common workflow language reference implementation
Home-page: https://github.com/common-workflow-language/cwltool
Download-URL: https://github.com/common-workflow-language/cwltool
Author: Common workflow language working group
Author-email: common-workflow-language@googlegroups.com
Classifier: Development Status :: 5 - Production/Stable
Classifier: Environment :: Console
Classifier: Intended Audience :: Developers
Classifier: Intended Audience :: Science/Research
Classifier: Intended Audience :: Healthcare Industry
Classifier: License :: OSI Approved :: Apache Software License
Classifier: Natural Language :: English
Classifier: Operating System :: MacOS :: MacOS X
Classifier: Operating System :: POSIX
Classifier: Operating System :: POSIX :: Linux
Classifier: Programming Language :: Python :: 3
Classifier: Programming Language :: Python :: 3.10
Classifier: Programming Language :: Python :: 3.11
Classifier: Programming Language :: Python :: 3.12
Classifier: Programming Language :: Python :: 3.13
Classifier: Programming Language :: Python :: 3.14
Classifier: Topic :: Scientific/Engineering
Classifier: Topic :: Scientific/Engineering :: Bio-Informatics
Classifier: Topic :: Scientific/Engineering :: Astronomy
Classifier: Topic :: Scientific/Engineering :: Atmospheric Science
Classifier: Topic :: Scientific/Engineering :: Information Analysis
Classifier: Topic :: Scientific/Engineering :: Medical Science Apps.
Classifier: Topic :: System :: Distributed Computing
Classifier: Topic :: Utilities
Requires-Python: >=3.10, <3.15
License-File: LICENSE.txt
Requires-Dist: requests>=2.6.1
Requires-Dist: ruamel.yaml<0.20,>=0.16
Requires-Dist: rdflib<7.6.0,>=4.2.2
Requires-Dist: schema-salad<9,>=8.9
Requires-Dist: prov==1.5.1
Requires-Dist: mypy-extensions
Requires-Dist: psutil>=5.6.6
Requires-Dist: coloredlogs
Requires-Dist: pydot>=1.4.1
Requires-Dist: argcomplete>=1.12.0
Requires-Dist: pyparsing!=3.0.2
Requires-Dist: cwl-utils>=0.32
Requires-Dist: spython>=0.3.0
Requires-Dist: rich-argparse
Requires-Dist: typing-extensions>=4.1.0
Provides-Extra: deps
Requires-Dist: galaxy-tool-util!=23.0.1,!=23.0.2,!=23.0.3,!=23.0.4,!=23.0.5,<25.2,>=22.1.2; extra == "deps"
Requires-Dist: galaxy-util<25.2; extra == "deps"
Requires-Dist: pillow; extra == "deps"
Dynamic: author
Dynamic: author-email
Dynamic: classifier
Dynamic: description
Dynamic: description-content-type
Dynamic: download-url
Dynamic: home-page
Dynamic: license-file
Dynamic: provides-extra
Dynamic: requires-dist
Dynamic: requires-python
Dynamic: summary
